chewrap/__init__.py
chewrap/__main__.py
chewrap/arguments.json
chewrap/arguments.py
chewrap/core.py
chewrap/docker.py
chewrap/parser.py
chewrap/usage.py
chewrap-0.1.0.dist-info/DESCRIPTION.rst
chewrap-0.1.0.dist-info/METADATA
chewrap-0.1.0.dist-info/RECORD
chewrap-0.1.0.dist-info/WHEEL
chewrap-0.1.0.dist-info/entry_points.txt
chewrap-0.1.0.dist-info/metadata.json
chewrap-0.1.0.dist-info/top_level.txt
