Metadata-Version: 2.0
Name: chewrap
Version: 0.1.0
Summary: CheWrap is a basic wrapper around Docker to interact with Eclipse Che's CLI.
